sfrmaker/__init__.py
sfrmaker/_version.py
sfrmaker/base.py
sfrmaker/checks.py
sfrmaker/default_config.yml
sfrmaker/elevations.py
sfrmaker/fileio.py
sfrmaker/flows.py
sfrmaker/gis.py
sfrmaker/grid.py
sfrmaker/lines.py
sfrmaker/logger.py
sfrmaker/mf5to6.py
sfrmaker/nhdplus_utils.py
sfrmaker/observations.py
sfrmaker/preprocessing.py
sfrmaker/reaches.py
sfrmaker/rivdata.py
sfrmaker/routing.py
sfrmaker/sfrdata.py
sfrmaker/units.py
sfrmaker/utils.py
sfrmaker/test/__init__.py
sfrmaker/test/conftest.py
sfrmaker/test/test_data.py
sfrmaker/test/test_elevations.py
sfrmaker/test/test_examples.py
sfrmaker/test/test_fileio.py
sfrmaker/test/test_flows.py
sfrmaker/test/test_from_nhdplus.py
sfrmaker/test/test_from_yaml.py
sfrmaker/test/test_gis.py
sfrmaker/test/test_grid.py
sfrmaker/test/test_lines.py
sfrmaker/test/test_logger.py
sfrmaker/test/test_map.py
sfrmaker/test/test_mf5to6.py
sfrmaker/test/test_nhdplus_utils.py
sfrmaker/test/test_notebooks.py
sfrmaker/test/test_observations.py
sfrmaker/test/test_preprocessing.py
sfrmaker/test/test_routing.py
sfrmaker/test/test_sfr_data.py
sfrmaker/test/test_units.py
sfrmaker/test/test_utils.py
sfrmaker/test/test_version.py
sfrmaker-0.13.1.dist-info/licenses/LICENSE.md
sfrmaker-0.13.1.dist-info/METADATA
sfrmaker-0.13.1.dist-info/WHEEL
sfrmaker-0.13.1.dist-info/entry_points.txt
sfrmaker-0.13.1.dist-info/top_level.txt
sfrmaker-0.13.1.dist-info/RECORD
