Metadata-Version: 2.4
Name: sfrmaker
Version: 0.13.1
Summary: Rapid construction of MODFLOW SFR Package input from hydrography data
Author-email: Andrew Leaf <aleaf@usgs.gov>, Mike Fienen <mnfienen@usgs.gov>, Howard Reeves <hwreeves@usgs.gov>
License: License
Project-URL: documentation, https://doi-usgs.github.io/sfrmaker/latest/
Project-URL: repository, https://github.com/doi-usgs/sfrmaker
Keywords: MODFLOW,groundwater,hydrogeology
Classifier: Development Status :: 4 - Beta
Classifier: Intended Audience :: Science/Research
Classifier: Programming Language :: Python :: 3 :: Only
Classifier: Topic :: Scientific/Engineering :: Hydrology
Requires-Python: >=3.10
License-File: LICENSE.md
Requires-Dist: geopandas
Requires-Dist: gis-utils
Requires-Dist: fiona
Requires-Dist: flopy
Requires-Dist: modflow-export
Requires-Dist: netcdf4
Requires-Dist: numpy
Requires-Dist: pandas
Requires-Dist: pyproj
Requires-Dist: pyyaml
Requires-Dist: rasterio
Requires-Dist: rasterstats
Requires-Dist: rtree
Requires-Dist: scipy
Requires-Dist: shapely
Requires-Dist: xarray
Provides-Extra: optional
Requires-Dist: matplotlib; extra == "optional"
Provides-Extra: test
Requires-Dist: codecov; extra == "test"
Requires-Dist: coverage; extra == "test"
Requires-Dist: pytest; extra == "test"
Requires-Dist: pytest-timeout; extra == "test"
Provides-Extra: docs
Requires-Dist: matplotlib; extra == "docs"
Requires-Dist: modflow-export[optional]; extra == "docs"
Requires-Dist: ipython[kernel]; extra == "docs"
Requires-Dist: sphinx; extra == "docs"
Requires-Dist: numpydoc; extra == "docs"
Requires-Dist: nbsphinx; extra == "docs"
Requires-Dist: sphinx-copybutton; extra == "docs"
Requires-Dist: sphinx-rtd-theme; extra == "docs"
Dynamic: license-file
